OffSecIta/__init__.py
OffSecIta/corsi.py
OffSecIta/utils.py
OffSecIta-0.1.2.dist-info/METADATA
OffSecIta-0.1.2.dist-info/WHEEL
OffSecIta-0.1.2.dist-info/top_level.txt
OffSecIta-0.1.2.dist-info/RECORD
